app_scanner/__init__.py
app_scanner/_linux.py
app_scanner/_macos.py
app_scanner/_windows.py
installed_apps_scanner-0.1.0.dist-info/licenses/LICENSE
installed_apps_scanner-0.1.0.dist-info/METADATA
installed_apps_scanner-0.1.0.dist-info/WHEEL
installed_apps_scanner-0.1.0.dist-info/top_level.txt
installed_apps_scanner-0.1.0.dist-info/RECORD
