Metadata-Version: 2.4
Name: installed-apps-scanner
Version: 0.1.0
Summary: A cross-platform Python utility to find installed applications on Windows, macOS, and Linux.
Author-email: AIgrator <aigrator@gmail.com>
License-Expression: MIT
Project-URL: Homepage, https://github.com/AIgrator/app-scanner
Project-URL: Bug Tracker, https://github.com/AIgrator/app-scanner/issues
Keywords: app,scanner,cross-platform,applications,installed,windows,macos,linux
Classifier: Programming Language :: Python :: 3
Classifier: Operating System :: OS Independent
Classifier: Topic :: System :: Systems Administration
Classifier: Topic :: Desktop Environment
Requires-Python: >=3.7
License-File: LICENSE
Dynamic: license-file
